var_maps/arome_var_map.json
var_maps/era5land_var_map.json
var_maps/era5sl_var_map.json
weather_provider_api/__init__.py
weather_provider_api/app_config.py
weather_provider_api/core/__init__.py
weather_provider_api/core/base_model.py
weather_provider_api/core/errors/__init__.py
weather_provider_api/core/errors/additional_responses.py
weather_provider_api/core/errors/api_models.py
weather_provider_api/core/errors/exceptions.py
weather_provider_api/core/initializers/__init__.py
weather_provider_api/core/initializers/error_handling.py
weather_provider_api/core/initializers/headers.py
weather_provider_api/core/initializers/logging.py
weather_provider_api/core/initializers/monitoring.py
weather_provider_api/core/initializers/mounting.py
weather_provider_api/core/initializers/rate_limiter.py
weather_provider_api/core/initializers/validation.py
weather_provider_api/core/views.py
weather_provider_api/main.py
weather_provider_api/routers/__init__.py
weather_provider_api/routers/weather/__init__.py
weather_provider_api/routers/weather/api_models.py
weather_provider_api/routers/weather/api_view_v1.py
weather_provider_api/routers/weather/api_view_v2.py
weather_provider_api/routers/weather/base_models/__init__.py
weather_provider_api/routers/weather/base_models/model.py
weather_provider_api/routers/weather/base_models/source.py
weather_provider_api/routers/weather/controller.py
weather_provider_api/routers/weather/exceptions.py
weather_provider_api/routers/weather/repository/__init__.py
weather_provider_api/routers/weather/repository/repository.py
weather_provider_api/routers/weather/sources/__init__.py
weather_provider_api/routers/weather/sources/cds/__init__.py
weather_provider_api/routers/weather/sources/cds/cds.py
weather_provider_api/routers/weather/sources/cds/client/__init__.py
weather_provider_api/routers/weather/sources/cds/client/downloader.py
weather_provider_api/routers/weather/sources/cds/client/era5land_repository.py
weather_provider_api-2.4324.dist-info/LICENSE
weather_provider_api-2.4324.dist-info/LICENSES/Apache-2.0.txt
weather_provider_api-2.4324.dist-info/LICENSES/CC-BY-2.5.txt
weather_provider_api-2.4324.dist-info/LICENSES/MPL-2.0.txt
weather_provider_api-2.4324.dist-info/METADATA
weather_provider_api-2.4324.dist-info/WHEEL
weather_provider_api-2.4324.dist-info/entry_points.txt
weather_provider_api-2.4324.dist-info/RECORD
