Metadata-Version: 2.1
Name: weather_provider_api
Version: 2.4324
Summary: Weather Provider Libraries and API
Home-page: https://github.com/alliander-opensource/wpla/
License: MPL-2.0
Author: Verbindingsteam
Requires-Python: >=3.8,<3.12
Classifier: License :: OSI Approved
Classifier: Programming Language :: Python :: 3
Classifier: Programming Language :: Python :: 3.8
Classifier: Programming Language :: Python :: 3.9
Classifier: Programming Language :: Python :: 3.10
Classifier: Programming Language :: Python :: 3.11
Requires-Dist: accept-types (>=0.4.1,<0.5.0)
Requires-Dist: beautifulsoup4 (>=4.11.1,<5.0.0)
Requires-Dist: cfgrib (>=0.9.10.3,<0.10.0.0)
Requires-Dist: eccodes (>=1.5.0,<2.0.0)
Requires-Dist: ecmwflibs (==0.5.1)
Requires-Dist: fastapi (>=0.103.1,<0.104.0)
Requires-Dist: geopy (>=2.3.0,<3.0.0)
Requires-Dist: gunicorn (>=21.2.0,<22.0.0)
Requires-Dist: lxml (>=4.9.1,<5.0.0)
Requires-Dist: netcdf4 (>=1.6.2,<2.0.0)
Requires-Dist: numpy (>=1.24.4,<2.0.0)
Requires-Dist: pandas (==2.0.3)
Requires-Dist: requests (>=2.28.1,<3.0.0)
Requires-Dist: slowapi (>=0.1.7,<0.2.0)
Requires-Dist: starlette (>=0.27.0,<0.28.0)
Requires-Dist: starlette-prometheus (>=0.9.0,<0.10.0)
Requires-Dist: structlog (>=23.1.0,<24.0.0)
Requires-Dist: tomli (>=2.0.1,<3.0.0)
Requires-Dist: uvicorn (>=0.21.1,<0.22.0)
Requires-Dist: xarray (>=2022.8.0,<2023.0.0)
Project-URL: Repository, https://github.com/alliander-opensource/wpla/
